dbterd-1.23.0.dist-info/METADATA
dbterd-1.23.0.dist-info/WHEEL
dbterd-1.23.0.dist-info/entry_points.txt
dbterd-1.23.0.dist-info/licenses/LICENSE
dbterd/__init__.py
dbterd/__main__.py
dbterd/adapters/__init__.py
dbterd/adapters/algos/__init__.py
dbterd/adapters/algos/semantic.py
dbterd/adapters/algos/test_relationship.py
dbterd/adapters/targets/__init__.py
dbterd/adapters/targets/d2.py
dbterd/adapters/targets/dbml.py
dbterd/adapters/targets/drawdb.py
dbterd/adapters/targets/graphviz.py
dbterd/adapters/targets/mermaid.py
dbterd/adapters/targets/plantuml.py
dbterd/api/__init__.py
dbterd/cli/__init__.py
dbterd/cli/config.py
dbterd/cli/main.py
dbterd/cli/params.py
dbterd/config.py
dbterd/constants.py
dbterd/core/__init__.py
dbterd/core/adapters/__init__.py
dbterd/core/adapters/algo.py
dbterd/core/adapters/target.py
dbterd/core/builder/__init__.py
dbterd/core/builder/base_builder.py
dbterd/core/builder/json_builder.py
dbterd/core/builder/text_builder.py
dbterd/core/executor.py
dbterd/core/filter.py
dbterd/core/models.py
dbterd/core/protocols/__init__.py
dbterd/core/protocols/algo_adapter.py
dbterd/core/protocols/target_adapter.py
dbterd/core/registry/__init__.py
dbterd/core/registry/decorators.py
dbterd/core/registry/models.py
dbterd/core/registry/plugin_registry.py
dbterd/default.py
dbterd/helpers/__init__.py
dbterd/helpers/cli_messaging.py
dbterd/helpers/dict.py
dbterd/helpers/file.py
dbterd/helpers/jsonify.py
dbterd/helpers/log.py
dbterd/helpers/yaml.py
dbterd/include/config_templates/config_template__dbt_cloud.yml
dbterd/include/config_templates/config_template__dbt_core.yml
dbterd/include/graphql_queries/erd_query__semantic.gql
dbterd/include/graphql_queries/erd_query__test_relationship.gql
dbterd/main.py
dbterd/plugins/__init__.py
dbterd/plugins/dbt_cloud/__init__.py
dbterd/plugins/dbt_cloud/administrative.py
dbterd/plugins/dbt_cloud/discovery.py
dbterd/plugins/dbt_cloud/graphql.py
dbterd/plugins/dbt_cloud/query.py
dbterd/plugins/dbt_core/__init__.py
dbterd/plugins/dbt_core/dbt_invocation.py
dbterd/types.py
dbterd-1.23.0.dist-info/RECORD
