Metadata-Version: 2.1
Name: dbterd
Version: 1.23.0
Summary: Generate the ERD-as-a-code from dbt artifacts
Keywords: dbt,erd,entity-relationship-diagram,dbml,mermaid,plantuml,graphviz,d2,drawdb,data-modeling,data-documentation,dbt-cloud
Author-Email: Dat Nguyen <datnguye.it09@gmail.com>
Maintainer-Email: Dat Nguyen <datnguye.it09@gmail.com>
License: MIT License
Classifier: Development Status :: 5 - Production/Stable
Classifier: Environment :: Console
Classifier: Intended Audience :: Developers
Classifier: Intended Audience :: Information Technology
Classifier: License :: OSI Approved :: MIT License
Classifier: Operating System :: OS Independent
Classifier: Programming Language :: Python :: 3
Classifier: Programming Language :: Python :: 3.9
Classifier: Programming Language :: Python :: 3.10
Classifier: Programming Language :: Python :: 3.11
Classifier: Programming Language :: Python :: 3.12
Classifier: Topic :: Documentation
Classifier: Topic :: Software Development :: Documentation
Classifier: Topic :: Software Development :: Libraries :: Python Modules
Classifier: Topic :: Software Development :: Quality Assurance
Project-URL: Homepage, https://github.com/datnguye/dbterd
Project-URL: Repository, https://github.com/datnguye/dbterd
Project-URL: Documentation, https://dbterd.datnguyen.de/
Project-URL: Issues, https://github.com/datnguye/dbterd/issues
Requires-Python: >=3.9
Requires-Dist: click>=8.1.7
Requires-Dist: dbt-artifacts-parser>=0.10.0
Requires-Dist: requests>=2.32.3
Requires-Dist: tomli>=2.0.0; python_version < "3.11"
Provides-Extra: dev
Requires-Dist: dbt-core>=1.7.11; extra == "dev"
Requires-Dist: dbt-postgres>=1.7.11; extra == "dev"
Requires-Dist: pytest>=6.2.5; extra == "dev"
Requires-Dist: pytest-sugar>=0.9.6; extra == "dev"
Requires-Dist: coverage[toml]>=6.5.0; extra == "dev"
Requires-Dist: black>=24.3.0; extra == "dev"
Requires-Dist: ruff>=0.2.0; extra == "dev"
Requires-Dist: pre-commit>=2.20.0; extra == "dev"
Requires-Dist: poethepoet>=0.16.4; extra == "dev"
Requires-Dist: mkdocs>=1.4.2; extra == "dev"
Requires-Dist: mkdocs-minify-plugin>=0.6.4; extra == "dev"
Requires-Dist: mkdocs-material>=9.1.5; extra == "dev"
Requires-Dist: mike>=1.1.2; extra == "dev"
Requires-Dist: pdoc>=14.4.0; extra == "dev"
Requires-Dist: pdm-backend; extra == "dev"
Provides-Extra: test
Requires-Dist: pytest>=6.2.5; extra == "test"
Requires-Dist: pytest-sugar>=0.9.6; extra == "test"
Requires-Dist: coverage[toml]>=6.5.0; extra == "test"
Provides-Extra: docs
Requires-Dist: mkdocs>=1.4.2; extra == "docs"
Requires-Dist: mkdocs-minify-plugin>=0.6.4; extra == "docs"
Requires-Dist: mkdocs-material>=9.1.5; extra == "docs"
Requires-Dist: mike>=1.1.2; extra == "docs"
